teatelethon/__init__.py
teatelethon/custom.py
teatelethon/functions.py
teatelethon/helpers.py
teatelethon/hints.py
teatelethon/password.py
teatelethon/requestiter.py
teatelethon/sync.py
teatelethon/types.py
teatelethon/utils.py
teatelethon/version.py
teatelethon/_updates/__init__.py
teatelethon/_updates/entitycache.py
teatelethon/_updates/messagebox.py
teatelethon/_updates/session.py
teatelethon/client/__init__.py
teatelethon/client/account.py
teatelethon/client/auth.py
teatelethon/client/bots.py
teatelethon/client/buttons.py
teatelethon/client/chats.py
teatelethon/client/dialogs.py
teatelethon/client/downloads.py
teatelethon/client/messageparse.py
teatelethon/client/messages.py
teatelethon/client/telegrambaseclient.py
teatelethon/client/telegramclient.py
teatelethon/client/updates.py
teatelethon/client/uploads.py
teatelethon/client/users.py
teatelethon/crypto/__init__.py
teatelethon/crypto/aes.py
teatelethon/crypto/aesctr.py
teatelethon/crypto/authkey.py
teatelethon/crypto/cdndecrypter.py
teatelethon/crypto/factorization.py
teatelethon/crypto/libssl.py
teatelethon/crypto/rsa.py
teatelethon/errors/__init__.py
teatelethon/errors/common.py
teatelethon/errors/rpcbaseerrors.py
teatelethon/errors/rpcerrorlist.py
teatelethon/events/__init__.py
teatelethon/events/album.py
teatelethon/events/callbackquery.py
teatelethon/events/chataction.py
teatelethon/events/common.py
teatelethon/events/inlinequery.py
teatelethon/events/messagedeleted.py
teatelethon/events/messageedited.py
teatelethon/events/messageread.py
teatelethon/events/newmessage.py
teatelethon/events/raw.py
teatelethon/events/userupdate.py
teatelethon/extensions/__init__.py
teatelethon/extensions/binaryreader.py
teatelethon/extensions/html.py
teatelethon/extensions/markdown.py
teatelethon/extensions/messagepacker.py
teatelethon/network/__init__.py
teatelethon/network/authenticator.py
teatelethon/network/mtprotoplainsender.py
teatelethon/network/mtprotosender.py
teatelethon/network/mtprotostate.py
teatelethon-1.32.3.dist-info/LICENSE
teatelethon-1.32.3.dist-info/METADATA
teatelethon-1.32.3.dist-info/WHEEL
teatelethon-1.32.3.dist-info/top_level.txt
teatelethon-1.32.3.dist-info/RECORD
