Metadata-Version: 2.1
Name: teatelethon
Version: 1.32.3
Summary: Telethon for teagram
Home-page: https://github.com/itzlayz/tea-TL
Download-URL: https://github.com/itzlayz/tea-TL/releases
Author: Lonami Exo
Author-email: totufals@hotmail.com
License: MIT
Keywords: teagram teagramtl telegram api chat client library messaging mtproto
Classifier: Development Status :: 5 - Production/Stable
Classifier: Intended Audience :: Developers
Classifier: Topic :: Communications :: Chat
Classifier: License :: OSI Approved :: MIT License
Classifier: Programming Language :: Python :: 3
Classifier: Programming Language :: Python :: 3.5
Classifier: Programming Language :: Python :: 3.6
Classifier: Programming Language :: Python :: 3.7
Classifier: Programming Language :: Python :: 3.8
Requires-Python: >=3.5
License-File: LICENSE
Requires-Dist: pyaes
Requires-Dist: rsa
Provides-Extra: cryptg
Requires-Dist: cryptg ; extra == 'cryptg'
